[
  {
    "id": 1,
    "date": "2024-04-15",
    "account_name": "Account_1",
    "description": "Description for Account_1",
    "amount": -600
  },
  {
    "id": 2,
    "date": "2024-04-16",
    "account_name": "Account_2",
    "description": "Description for Account_2",
    "amount": 876
  },
  {
    "id": 3,
    "date": "2024-04-17",
    "account_name": "Account_3",
    "description": "Description for Account_3",
    "amount": -960
  },
  {
    "id": 4,
    "date": "2024-04-18",
    "account_name": "Account_4",
    "description": "Description for Account_4",
    "amount": 245
  },
  {
    "id": 5,
    "date": "2024-04-19",
    "account_name": "Account_5",
    "description": "Description for Account_5",
    "amount": -839
  },
  {
    "id": 6,
    "date": "2024-04-20",
    "account_name": "Account_6",
    "description": "Description for Account_6",
    "amount": 815
  },
  {
    "id": 7,
    "date": "2024-04-21",
    "account_name": "Account_7",
    "description": "Description for Account_7",
    "amount": -865
  },
  {
    "id": 8,
    "date": "2024-04-22",
    "account_name": "Account_8",
    "description": "Description for Account_8",
    "amount": -508
  },
  {
    "id": 9,
    "date": "2024-04-23",
    "account_name": "Account_9",
    "description": "Description for Account_9",
    "amount": -667
  },
  {
    "id": 10,
    "date": "2024-04-24",
    "account_name": "Account_10",
    "description": "Description for Account_10",
    "amount": 967
  },
  {
    "id": 11,
    "date": "2024-04-25",
    "account_name": "Account_11",
    "description": "Description for Account_11",
    "amount": 856
  },
  {
    "id": 12,
    "date": "2024-04-26",
    "account_name": "Account_12",
    "description": "Description for Account_12",
    "amount": 562
  },
  {
    "id": 13,
    "date": "2024-04-27",
    "account_name": "Account_13",
    "description": "Description for Account_13",
    "amount": 580
  },
  {
    "id": 14,
    "date": "2024-04-28",
    "account_name": "Account_14",
    "description": "Description for Account_14",
    "amount": 512
  },
  {
    "id": 15,
    "date": "2024-04-29",
    "account_name": "Account_15",
    "description": "Description for Account_15",
    "amount": -74
  },
  {
    "id": 16,
    "date": "2024-04-30",
    "account_name": "Account_16",
    "description": "Description for Account_16",
    "amount": 529
  },
  {
    "id": 17,
    "date": "2024-05-01",
    "account_name": "Account_17",
    "description": "Description for Account_17",
    "amount": 925
  },
  {
    "id": 18,
    "date": "2024-05-02",
    "account_name": "Account_18",
    "description": "Description for Account_18",
    "amount": 128
  },
  {
    "id": 19,
    "date": "2024-05-03",
    "account_name": "Account_19",
    "description": "Description for Account_19",
    "amount": -32
  },
  {
    "id": 20,
    "date": "2024-05-04",
    "account_name": "Account_20",
    "description": "Description for Account_20",
    "amount": -857
  },
  {
    "id": 21,
    "date": "2024-05-05",
    "account_name": "Account_21",
    "description": "Description for Account_21",
    "amount": -224
  },
  {
    "id": 22,
    "date": "2024-05-06",
    "account_name": "Account_22",
    "description": "Description for Account_22",
    "amount": -599
  },
  {
    "id": 23,
    "date": "2024-05-07",
    "account_name": "Account_23",
    "description": "Description for Account_23",
    "amount": -741
  },
  {
    "id": 24,
    "date": "2024-05-08",
    "account_name": "Account_24",
    "description": "Description for Account_24",
    "amount": 945
  },
  {
    "id": 25,
    "date": "2024-05-09",
    "account_name": "Account_25",
    "description": "Description for Account_25",
    "amount": -72
  },
  {
    "id": 26,
    "date": "2024-05-10",
    "account_name": "Account_26",
    "description": "Description for Account_26",
    "amount": -612
  },
  {
    "id": 27,
    "date": "2024-05-11",
    "account_name": "Account_27",
    "description": "Description for Account_27",
    "amount": -557
  },
  {
    "id": 28,
    "date": "2024-05-12",
    "account_name": "Account_28",
    "description": "Description for Account_28",
    "amount": -558
  },
  {
    "id": 29,
    "date": "2024-05-13",
    "account_name": "Account_29",
    "description": "Description for Account_29",
    "amount": 735
  },
  {
    "id": 30,
    "date": "2024-05-14",
    "account_name": "Account_30",
    "description": "Description for Account_30",
    "amount": 681
  },
  {
    "id": 31,
    "date": "2024-05-15",
    "account_name": "Account_31",
    "description": "Description for Account_31",
    "amount": -501
  },
  {
    "id": 32,
    "date": "2024-05-16",
    "account_name": "Account_32",
    "description": "Description for Account_32",
    "amount": 390
  },
  {
    "id": 33,
    "date": "2024-05-17",
    "account_name": "Account_33",
    "description": "Description for Account_33",
    "amount": 543
  },
  {
    "id": 34,
    "date": "2024-05-18",
    "account_name": "Account_34",
    "description": "Description for Account_34",
    "amount": 1
  },
  {
    "id": 35,
    "date": "2024-05-19",
    "account_name": "Account_35",
    "description": "Description for Account_35",
    "amount": -11
  },
  {
    "id": 36,
    "date": "2024-05-20",
    "account_name": "Account_36",
    "description": "Description for Account_36",
    "amount": -375
  },
  {
    "id": 37,
    "date": "2024-05-21",
    "account_name": "Account_37",
    "description": "Description for Account_37",
    "amount": 296
  },
  {
    "id": 38,
    "date": "2024-05-22",
    "account_name": "Account_38",
    "description": "Description for Account_38",
    "amount": -818
  },
  {
    "id": 39,
    "date": "2024-05-23",
    "account_name": "Account_39",
    "description": "Description for Account_39",
    "amount": 980
  },
  {
    "id": 40,
    "date": "2024-05-24",
    "account_name": "Account_40",
    "description": "Description for Account_40",
    "amount": -653
  },
  {
    "id": 41,
    "date": "2024-05-25",
    "account_name": "Account_41",
    "description": "Description for Account_41",
    "amount": -677
  },
  {
    "id": 42,
    "date": "2024-05-26",
    "account_name": "Account_42",
    "description": "Description for Account_42",
    "amount": -331
  },
  {
    "id": 43,
    "date": "2024-05-27",
    "account_name": "Account_43",
    "description": "Description for Account_43",
    "amount": -555
  },
  {
    "id": 44,
    "date": "2024-05-28",
    "account_name": "Account_44",
    "description": "Description for Account_44",
    "amount": -293
  },
  {
    "id": 45,
    "date": "2024-05-29",
    "account_name": "Account_45",
    "description": "Description for Account_45",
    "amount": -635
  },
  {
    "id": 46,
    "date": "2024-05-30",
    "account_name": "Account_46",
    "description": "Description for Account_46",
    "amount": 41
  },
  {
    "id": 47,
    "date": "2024-05-31",
    "account_name": "Account_47",
    "description": "Description for Account_47",
    "amount": 239
  },
  {
    "id": 48,
    "date": "2024-06-01",
    "account_name": "Account_48",
    "description": "Description for Account_48",
    "amount": -655
  },
  {
    "id": 49,
    "date": "2024-06-02",
    "account_name": "Account_49",
    "description": "Description for Account_49",
    "amount": -453
  },
  {
    "id": 50,
    "date": "2024-06-03",
    "account_name": "Account_50",
    "description": "Description for Account_50",
    "amount": 154
  },
  {
    "id": 51,
    "date": "2024-06-04",
    "account_name": "Account_51",
    "description": "Description for Account_51",
    "amount": 989
  },
  {
    "id": 52,
    "date": "2024-06-05",
    "account_name": "Account_52",
    "description": "Description for Account_52",
    "amount": 889
  },
  {
    "id": 53,
    "date": "2024-06-06",
    "account_name": "Account_53",
    "description": "Description for Account_53",
    "amount": -503
  },
  {
    "id": 54,
    "date": "2024-06-07",
    "account_name": "Account_54",
    "description": "Description for Account_54",
    "amount": 724
  },
  {
    "id": 55,
    "date": "2024-06-08",
    "account_name": "Account_55",
    "description": "Description for Account_55",
    "amount": -660
  },
  {
    "id": 56,
    "date": "2024-06-09",
    "account_name": "Account_56",
    "description": "Description for Account_56",
    "amount": 898
  },
  {
    "id": 57,
    "date": "2024-06-10",
    "account_name": "Account_57",
    "description": "Description for Account_57",
    "amount": -916
  },
  {
    "id": 58,
    "date": "2024-06-11",
    "account_name": "Account_58",
    "description": "Description for Account_58",
    "amount": -490
  },
  {
    "id": 59,
    "date": "2024-06-12",
    "account_name": "Account_59",
    "description": "Description for Account_59",
    "amount": -871
  },
  {
    "id": 60,
    "date": "2024-06-13",
    "account_name": "Account_60",
    "description": "Description for Account_60",
    "amount": -598
  },
  {
    "id": 61,
    "date": "2024-06-14",
    "account_name": "Account_61",
    "description": "Description for Account_61",
    "amount": -224
  },
  {
    "id": 62,
    "date": "2024-06-15",
    "account_name": "Account_62",
    "description": "Description for Account_62",
    "amount": -906
  },
  {
    "id": 63,
    "date": "2024-06-16",
    "account_name": "Account_63",
    "description": "Description for Account_63",
    "amount": 811
  },
  {
    "id": 64,
    "date": "2024-06-17",
    "account_name": "Account_64",
    "description": "Description for Account_64",
    "amount": -392
  },
  {
    "id": 65,
    "date": "2024-06-18",
    "account_name": "Account_65",
    "description": "Description for Account_65",
    "amount": 947
  },
  {
    "id": 66,
    "date": "2024-06-19",
    "account_name": "Account_66",
    "description": "Description for Account_66",
    "amount": -781
  },
  {
    "id": 67,
    "date": "2024-06-20",
    "account_name": "Account_67",
    "description": "Description for Account_67",
    "amount": -485
  },
  {
    "id": 68,
    "date": "2024-06-21",
    "account_name": "Account_68",
    "description": "Description for Account_68",
    "amount": 384
  },
  {
    "id": 69,
    "date": "2024-06-22",
    "account_name": "Account_69",
    "description": "Description for Account_69",
    "amount": -570
  },
  {
    "id": 70,
    "date": "2024-06-23",
    "account_name": "Account_70",
    "description": "Description for Account_70",
    "amount": 146
  },
  {
    "id": 71,
    "date": "2024-06-24",
    "account_name": "Account_71",
    "description": "Description for Account_71",
    "amount": -810
  },
  {
    "id": 72,
    "date": "2024-06-25",
    "account_name": "Account_72",
    "description": "Description for Account_72",
    "amount": -801
  },
  {
    "id": 73,
    "date": "2024-06-26",
    "account_name": "Account_73",
    "description": "Description for Account_73",
    "amount": 609
  },
  {
    "id": 74,
    "date": "2024-06-27",
    "account_name": "Account_74",
    "description": "Description for Account_74",
    "amount": -69
  },
  {
    "id": 75,
    "date": "2024-06-28",
    "account_name": "Account_75",
    "description": "Description for Account_75",
    "amount": 120
  },
  {
    "id": 76,
    "date": "2024-06-29",
    "account_name": "Account_76",
    "description": "Description for Account_76",
    "amount": 451
  },
  {
    "id": 77,
    "date": "2024-06-30",
    "account_name": "Account_77",
    "description": "Description for Account_77",
    "amount": 100
  },
  {
    "id": 78,
    "date": "2024-07-01",
    "account_name": "Account_78",
    "description": "Description for Account_78",
    "amount": -969
  },
  {
    "id": 79,
    "date": "2024-07-02",
    "account_name": "Account_79",
    "description": "Description for Account_79",
    "amount": -627
  },
  {
    "id": 80,
    "date": "2024-07-03",
    "account_name": "Account_80",
    "description": "Description for Account_80",
    "amount": 94
  },
  {
    "id": 81,
    "date": "2024-07-04",
    "account_name": "Account_81",
    "description": "Description for Account_81",
    "amount": 183
  },
  {
    "id": 82,
    "date": "2024-07-05",
    "account_name": "Account_82",
    "description": "Description for Account_82",
    "amount": -210
  },
  {
    "id": 83,
    "date": "2024-07-06",
    "account_name": "Account_83",
    "description": "Description for Account_83",
    "amount": -513
  },
  {
    "id": 84,
    "date": "2024-07-07",
    "account_name": "Account_84",
    "description": "Description for Account_84",
    "amount": -803
  },
  {
    "id": 85,
    "date": "2024-07-08",
    "account_name": "Account_85",
    "description": "Description for Account_85",
    "amount": 970
  },
  {
    "id": 86,
    "date": "2024-07-09",
    "account_name": "Account_86",
    "description": "Description for Account_86",
    "amount": 326
  },
  {
    "id": 87,
    "date": "2024-07-10",
    "account_name": "Account_87",
    "description": "Description for Account_87",
    "amount": -623
  },
  {
    "id": 88,
    "date": "2024-07-11",
    "account_name": "Account_88",
    "description": "Description for Account_88",
    "amount": 569
  },
  {
    "id": 89,
    "date": "2024-07-12",
    "account_name": "Account_89",
    "description": "Description for Account_89",
    "amount": -649
  },
  {
    "id": 90,
    "date": "2024-07-13",
    "account_name": "Account_90",
    "description": "Description for Account_90",
    "amount": -555
  },
  {
    "id": 91,
    "date": "2024-07-14",
    "account_name": "Account_91",
    "description": "Description for Account_91",
    "amount": 536
  },
  {
    "id": 92,
    "date": "2024-07-15",
    "account_name": "Account_92",
    "description": "Description for Account_92",
    "amount": 955
  },
  {
    "id": 93,
    "date": "2024-07-16",
    "account_name": "Account_93",
    "description": "Description for Account_93",
    "amount": -665
  },
  {
    "id": 94,
    "date": "2024-07-17",
    "account_name": "Account_94",
    "description": "Description for Account_94",
    "amount": 327
  },
  {
    "id": 95,
    "date": "2024-07-18",
    "account_name": "Account_95",
    "description": "Description for Account_95",
    "amount": 770
  },
  {
    "id": 96,
    "date": "2024-07-19",
    "account_name": "Account_96",
    "description": "Description for Account_96",
    "amount": 922
  },
  {
    "id": 97,
    "date": "2024-07-20",
    "account_name": "Account_97",
    "description": "Description for Account_97",
    "amount": -784
  },
  {
    "id": 98,
    "date": "2024-07-21",
    "account_name": "Account_98",
    "description": "Description for Account_98",
    "amount": -492
  },
  {
    "id": 99,
    "date": "2024-07-22",
    "account_name": "Account_99",
    "description": "Description for Account_99",
    "amount": -855
  },
  {
    "id": 100,
    "date": "2024-07-23",
    "account_name": "Account_100",
    "description": "Description for Account_100",
    "amount": 562
  },
  {
    "id": 101,
    "date": "2024-07-24",
    "account_name": "Account_101",
    "description": "Description for Account_101",
    "amount": -645
  },
  {
    "id": 102,
    "date": "2024-07-25",
    "account_name": "Account_102",
    "description": "Description for Account_102",
    "amount": 535
  },
  {
    "id": 103,
    "date": "2024-07-26",
    "account_name": "Account_103",
    "description": "Description for Account_103",
    "amount": 790
  },
  {
    "id": 104,
    "date": "2024-07-27",
    "account_name": "Account_104",
    "description": "Description for Account_104",
    "amount": -213
  },
  {
    "id": 105,
    "date": "2024-07-28",
    "account_name": "Account_105",
    "description": "Description for Account_105",
    "amount": 496
  },
  {
    "id": 106,
    "date": "2024-07-29",
    "account_name": "Account_106",
    "description": "Description for Account_106",
    "amount": 523
  },
  {
    "id": 107,
    "date": "2024-07-30",
    "account_name": "Account_107",
    "description": "Description for Account_107",
    "amount": 60
  },
  {
    "id": 108,
    "date": "2024-07-31",
    "account_name": "Account_108",
    "description": "Description for Account_108",
    "amount": 731
  },
  {
    "id": 109,
    "date": "2024-08-01",
    "account_name": "Account_109",
    "description": "Description for Account_109",
    "amount": 635
  },
  {
    "id": 110,
    "date": "2024-08-02",
    "account_name": "Account_110",
    "description": "Description for Account_110",
    "amount": -794
  },
  {
    "id": 111,
    "date": "2024-08-03",
    "account_name": "Account_111",
    "description": "Description for Account_111",
    "amount": -751
  },
  {
    "id": 112,
    "date": "2024-08-04",
    "account_name": "Account_112",
    "description": "Description for Account_112",
    "amount": 121
  },
  {
    "id": 113,
    "date": "2024-08-05",
    "account_name": "Account_113",
    "description": "Description for Account_113",
    "amount": 889
  },
  {
    "id": 114,
    "date": "2024-08-06",
    "account_name": "Account_114",
    "description": "Description for Account_114",
    "amount": 811
  },
  {
    "id": 115,
    "date": "2024-08-07",
    "account_name": "Account_115",
    "description": "Description for Account_115",
    "amount": -273
  },
  {
    "id": 116,
    "date": "2024-08-08",
    "account_name": "Account_116",
    "description": "Description for Account_116",
    "amount": -618
  },
  {
    "id": 117,
    "date": "2024-08-09",
    "account_name": "Account_117",
    "description": "Description for Account_117",
    "amount": -147
  },
  {
    "id": 118,
    "date": "2024-08-10",
    "account_name": "Account_118",
    "description": "Description for Account_118",
    "amount": -770
  },
  {
    "id": 119,
    "date": "2024-08-11",
    "account_name": "Account_119",
    "description": "Description for Account_119",
    "amount": 110
  },
  {
    "id": 120,
    "date": "2024-08-12",
    "account_name": "Account_120",
    "description": "Description for Account_120",
    "amount": -319
  },
  {
    "id": 121,
    "date": "2024-08-13",
    "account_name": "Account_121",
    "description": "Description for Account_121",
    "amount": -775
  },
  {
    "id": 122,
    "date": "2024-08-14",
    "account_name": "Account_122",
    "description": "Description for Account_122",
    "amount": -682
  },
  {
    "id": 123,
    "date": "2024-08-15",
    "account_name": "Account_123",
    "description": "Description for Account_123",
    "amount": 251
  },
  {
    "id": 124,
    "date": "2024-08-16",
    "account_name": "Account_124",
    "description": "Description for Account_124",
    "amount": -214
  },
  {
    "id": 125,
    "date": "2024-08-17",
    "account_name": "Account_125",
    "description": "Description for Account_125",
    "amount": -17
  },
  {
    "id": 126,
    "date": "2024-08-18",
    "account_name": "Account_126",
    "description": "Description for Account_126",
    "amount": 703
  },
  {
    "id": 127,
    "date": "2024-08-19",
    "account_name": "Account_127",
    "description": "Description for Account_127",
    "amount": 325
  },
  {
    "id": 128,
    "date": "2024-08-20",
    "account_name": "Account_128",
    "description": "Description for Account_128",
    "amount": -794
  },
  {
    "id": 129,
    "date": "2024-08-21",
    "account_name": "Account_129",
    "description": "Description for Account_129",
    "amount": -375
  },
  {
    "id": 130,
    "date": "2024-08-22",
    "account_name": "Account_130",
    "description": "Description for Account_130",
    "amount": 684
  },
  {
    "id": 131,
    "date": "2024-08-23",
    "account_name": "Account_131",
    "description": "Description for Account_131",
    "amount": 774
  },
  {
    "id": 132,
    "date": "2024-08-24",
    "account_name": "Account_132",
    "description": "Description for Account_132",
    "amount": -328
  },
  {
    "id": 133,
    "date": "2024-08-25",
    "account_name": "Account_133",
    "description": "Description for Account_133",
    "amount": -696
  },
  {
    "id": 134,
    "date": "2024-08-26",
    "account_name": "Account_134",
    "description": "Description for Account_134",
    "amount": 577
  },
  {
    "id": 135,
    "date": "2024-08-27",
    "account_name": "Account_135",
    "description": "Description for Account_135",
    "amount": -356
  },
  {
    "id": 136,
    "date": "2024-08-28",
    "account_name": "Account_136",
    "description": "Description for Account_136",
    "amount": -559
  },
  {
    "id": 137,
    "date": "2024-08-29",
    "account_name": "Account_137",
    "description": "Description for Account_137",
    "amount": 23
  },
  {
    "id": 138,
    "date": "2024-08-30",
    "account_name": "Account_138",
    "description": "Description for Account_138",
    "amount": -65
  },
  {
    "id": 139,
    "date": "2024-08-31",
    "account_name": "Account_139",
    "description": "Description for Account_139",
    "amount": -582
  },
  {
    "id": 140,
    "date": "2024-09-01",
    "account_name": "Account_140",
    "description": "Description for Account_140",
    "amount": 830
  },
  {
    "id": 141,
    "date": "2024-09-02",
    "account_name": "Account_141",
    "description": "Description for Account_141",
    "amount": 477
  },
  {
    "id": 142,
    "date": "2024-09-03",
    "account_name": "Account_142",
    "description": "Description for Account_142",
    "amount": 100
  },
  {
    "id": 143,
    "date": "2024-09-04",
    "account_name": "Account_143",
    "description": "Description for Account_143",
    "amount": -443
  },
  {
    "id": 144,
    "date": "2024-09-05",
    "account_name": "Account_144",
    "description": "Description for Account_144",
    "amount": 521
  },
  {
    "id": 145,
    "date": "2024-09-06",
    "account_name": "Account_145",
    "description": "Description for Account_145",
    "amount": -312
  },
  {
    "id": 146,
    "date": "2024-09-07",
    "account_name": "Account_146",
    "description": "Description for Account_146",
    "amount": 516
  },
  {
    "id": 147,
    "date": "2024-09-08",
    "account_name": "Account_147",
    "description": "Description for Account_147",
    "amount": 646
  },
  {
    "id": 148,
    "date": "2024-09-09",
    "account_name": "Account_148",
    "description": "Description for Account_148",
    "amount": -913
  },
  {
    "id": 149,
    "date": "2024-09-10",
    "account_name": "Account_149",
    "description": "Description for Account_149",
    "amount": 356
  },
  {
    "id": 150,
    "date": "2024-09-11",
    "account_name": "Account_150",
    "description": "Description for Account_150",
    "amount": -112
  },
  {
    "id": 151,
    "date": "2024-09-12",
    "account_name": "Account_151",
    "description": "Description for Account_151",
    "amount": 252
  },
  {
    "id": 152,
    "date": "2024-09-13",
    "account_name": "Account_152",
    "description": "Description for Account_152",
    "amount": 275
  },
  {
    "id": 153,
    "date": "2024-09-14",
    "account_name": "Account_153",
    "description": "Description for Account_153",
    "amount": -341
  },
  {
    "id": 154,
    "date": "2024-09-15",
    "account_name": "Account_154",
    "description": "Description for Account_154",
    "amount": -695
  },
  {
    "id": 155,
    "date": "2024-09-16",
    "account_name": "Account_155",
    "description": "Description for Account_155",
    "amount": -801
  },
  {
    "id": 156,
    "date": "2024-09-17",
    "account_name": "Account_156",
    "description": "Description for Account_156",
    "amount": 531
  },
  {
    "id": 157,
    "date": "2024-09-18",
    "account_name": "Account_157",
    "description": "Description for Account_157",
    "amount": -765
  },
  {
    "id": 158,
    "date": "2024-09-19",
    "account_name": "Account_158",
    "description": "Description for Account_158",
    "amount": -397
  },
  {
    "id": 159,
    "date": "2024-09-20",
    "account_name": "Account_159",
    "description": "Description for Account_159",
    "amount": 516
  },
  {
    "id": 160,
    "date": "2024-09-21",
    "account_name": "Account_160",
    "description": "Description for Account_160",
    "amount": 68
  },
  {
    "id": 161,
    "date": "2024-09-22",
    "account_name": "Account_161",
    "description": "Description for Account_161",
    "amount": -865
  },
  {
    "id": 162,
    "date": "2024-09-23",
    "account_name": "Account_162",
    "description": "Description for Account_162",
    "amount": -675
  },
  {
    "id": 163,
    "date": "2024-09-24",
    "account_name": "Account_163",
    "description": "Description for Account_163",
    "amount": -119
  },
  {
    "id": 164,
    "date": "2024-09-25",
    "account_name": "Account_164",
    "description": "Description for Account_164",
    "amount": 228
  },
  {
    "id": 165,
    "date": "2024-09-26",
    "account_name": "Account_165",
    "description": "Description for Account_165",
    "amount": -382
  },
  {
    "id": 166,
    "date": "2024-09-27",
    "account_name": "Account_166",
    "description": "Description for Account_166",
    "amount": 620
  },
  {
    "id": 167,
    "date": "2024-09-28",
    "account_name": "Account_167",
    "description": "Description for Account_167",
    "amount": 191
  },
  {
    "id": 168,
    "date": "2024-09-29",
    "account_name": "Account_168",
    "description": "Description for Account_168",
    "amount": -811
  },
  {
    "id": 169,
    "date": "2024-09-30",
    "account_name": "Account_169",
    "description": "Description for Account_169",
    "amount": -530
  },
  {
    "id": 170,
    "date": "2024-10-01",
    "account_name": "Account_170",
    "description": "Description for Account_170",
    "amount": 28
  },
  {
    "id": 171,
    "date": "2024-10-02",
    "account_name": "Account_171",
    "description": "Description for Account_171",
    "amount": 639
  },
  {
    "id": 172,
    "date": "2024-10-03",
    "account_name": "Account_172",
    "description": "Description for Account_172",
    "amount": 196
  },
  {
    "id": 173,
    "date": "2024-10-04",
    "account_name": "Account_173",
    "description": "Description for Account_173",
    "amount": 427
  },
  {
    "id": 174,
    "date": "2024-10-05",
    "account_name": "Account_174",
    "description": "Description for Account_174",
    "amount": -527
  },
  {
    "id": 175,
    "date": "2024-10-06",
    "account_name": "Account_175",
    "description": "Description for Account_175",
    "amount": 235
  },
  {
    "id": 176,
    "date": "2024-10-07",
    "account_name": "Account_176",
    "description": "Description for Account_176",
    "amount": 122
  },
  {
    "id": 177,
    "date": "2024-10-08",
    "account_name": "Account_177",
    "description": "Description for Account_177",
    "amount": 149
  },
  {
    "id": 178,
    "date": "2024-10-09",
    "account_name": "Account_178",
    "description": "Description for Account_178",
    "amount": 61
  },
  {
    "id": 179,
    "date": "2024-10-10",
    "account_name": "Account_179",
    "description": "Description for Account_179",
    "amount": 623
  },
  {
    "id": 180,
    "date": "2024-10-11",
    "account_name": "Account_180",
    "description": "Description for Account_180",
    "amount": -175
  },
  {
    "id": 181,
    "date": "2024-10-12",
    "account_name": "Account_181",
    "description": "Description for Account_181",
    "amount": 236
  },
  {
    "id": 182,
    "date": "2024-10-13",
    "account_name": "Account_182",
    "description": "Description for Account_182",
    "amount": -680
  },
  {
    "id": 183,
    "date": "2024-10-14",
    "account_name": "Account_183",
    "description": "Description for Account_183",
    "amount": -391
  },
  {
    "id": 184,
    "date": "2024-10-15",
    "account_name": "Account_184",
    "description": "Description for Account_184",
    "amount": -294
  },
  {
    "id": 185,
    "date": "2024-10-16",
    "account_name": "Account_185",
    "description": "Description for Account_185",
    "amount": -832
  },
  {
    "id": 186,
    "date": "2024-10-17",
    "account_name": "Account_186",
    "description": "Description for Account_186",
    "amount": -572
  },
  {
    "id": 187,
    "date": "2024-10-18",
    "account_name": "Account_187",
    "description": "Description for Account_187",
    "amount": -467
  },
  {
    "id": 188,
    "date": "2024-10-19",
    "account_name": "Account_188",
    "description": "Description for Account_188",
    "amount": 730
  },
  {
    "id": 189,
    "date": "2024-10-20",
    "account_name": "Account_189",
    "description": "Description for Account_189",
    "amount": 327
  },
  {
    "id": 190,
    "date": "2024-10-21",
    "account_name": "Account_190",
    "description": "Description for Account_190",
    "amount": -256
  },
  {
    "id": 191,
    "date": "2024-10-22",
    "account_name": "Account_191",
    "description": "Description for Account_191",
    "amount": 290
  },
  {
    "id": 192,
    "date": "2024-10-23",
    "account_name": "Account_192",
    "description": "Description for Account_192",
    "amount": -633
  },
  {
    "id": 193,
    "date": "2024-10-24",
    "account_name": "Account_193",
    "description": "Description for Account_193",
    "amount": 197
  },
  {
    "id": 194,
    "date": "2024-10-25",
    "account_name": "Account_194",
    "description": "Description for Account_194",
    "amount": -975
  },
  {
    "id": 195,
    "date": "2024-10-26",
    "account_name": "Account_195",
    "description": "Description for Account_195",
    "amount": 109
  },
  {
    "id": 196,
    "date": "2024-10-27",
    "account_name": "Account_196",
    "description": "Description for Account_196",
    "amount": 272
  },
  {
    "id": 197,
    "date": "2024-10-28",
    "account_name": "Account_197",
    "description": "Description for Account_197",
    "amount": 699
  },
  {
    "id": 198,
    "date": "2024-10-29",
    "account_name": "Account_198",
    "description": "Description for Account_198",
    "amount": 805
  },
  {
    "id": 199,
    "date": "2024-10-30",
    "account_name": "Account_199",
    "description": "Description for Account_199",
    "amount": 694
  },
  {
    "id": 200,
    "date": "2024-10-31",
    "account_name": "Account_200",
    "description": "Description for Account_200",
    "amount": 783
  },
  {
    "id": 201,
    "date": "2024-11-01",
    "account_name": "Account_201",
    "description": "Description for Account_201",
    "amount": 846
  },
  {
    "id": 202,
    "date": "2024-11-02",
    "account_name": "Account_202",
    "description": "Description for Account_202",
    "amount": -509
  },
  {
    "id": 203,
    "date": "2024-11-03",
    "account_name": "Account_203",
    "description": "Description for Account_203",
    "amount": -707
  },
  {
    "id": 204,
    "date": "2024-11-04",
    "account_name": "Account_204",
    "description": "Description for Account_204",
    "amount": 255
  },
  {
    "id": 205,
    "date": "2024-11-05",
    "account_name": "Account_205",
    "description": "Description for Account_205",
    "amount": 364
  },
  {
    "id": 206,
    "date": "2024-11-06",
    "account_name": "Account_206",
    "description": "Description for Account_206",
    "amount": 156
  },
  {
    "id": 207,
    "date": "2024-11-07",
    "account_name": "Account_207",
    "description": "Description for Account_207",
    "amount": -513
  },
  {
    "id": 208,
    "date": "2024-11-08",
    "account_name": "Account_208",
    "description": "Description for Account_208",
    "amount": -924
  },
  {
    "id": 209,
    "date": "2024-11-09",
    "account_name": "Account_209",
    "description": "Description for Account_209",
    "amount": 835
  },
  {
    "id": 210,
    "date": "2024-11-10",
    "account_name": "Account_210",
    "description": "Description for Account_210",
    "amount": -775
  },
  {
    "id": 211,
    "date": "2024-11-11",
    "account_name": "Account_211",
    "description": "Description for Account_211",
    "amount": 623
  },
  {
    "id": 212,
    "date": "2024-11-12",
    "account_name": "Account_212",
    "description": "Description for Account_212",
    "amount": -142
  },
  {
    "id": 213,
    "date": "2024-11-13",
    "account_name": "Account_213",
    "description": "Description for Account_213",
    "amount": -828
  },
  {
    "id": 214,
    "date": "2024-11-14",
    "account_name": "Account_214",
    "description": "Description for Account_214",
    "amount": 46
  },
  {
    "id": 215,
    "date": "2024-11-15",
    "account_name": "Account_215",
    "description": "Description for Account_215",
    "amount": -658
  },
  {
    "id": 216,
    "date": "2024-11-16",
    "account_name": "Account_216",
    "description": "Description for Account_216",
    "amount": -798
  },
  {
    "id": 217,
    "date": "2024-11-17",
    "account_name": "Account_217",
    "description": "Description for Account_217",
    "amount": -667
  },
  {
    "id": 218,
    "date": "2024-11-18",
    "account_name": "Account_218",
    "description": "Description for Account_218",
    "amount": 538
  },
  {
    "id": 219,
    "date": "2024-11-19",
    "account_name": "Account_219",
    "description": "Description for Account_219",
    "amount": 475
  },
  {
    "id": 220,
    "date": "2024-11-20",
    "account_name": "Account_220",
    "description": "Description for Account_220",
    "amount": -154
  },
  {
    "id": 221,
    "date": "2024-11-21",
    "account_name": "Account_221",
    "description": "Description for Account_221",
    "amount": -169
  },
  {
    "id": 222,
    "date": "2024-11-22",
    "account_name": "Account_222",
    "description": "Description for Account_222",
    "amount": 831
  },
  {
    "id": 223,
    "date": "2024-11-23",
    "account_name": "Account_223",
    "description": "Description for Account_223",
    "amount": -371
  },
  {
    "id": 224,
    "date": "2024-11-24",
    "account_name": "Account_224",
    "description": "Description for Account_224",
    "amount": 169
  },
  {
    "id": 225,
    "date": "2024-11-25",
    "account_name": "Account_225",
    "description": "Description for Account_225",
    "amount": -325
  },
  {
    "id": 226,
    "date": "2024-11-26",
    "account_name": "Account_226",
    "description": "Description for Account_226",
    "amount": 699
  },
  {
    "id": 227,
    "date": "2024-11-27",
    "account_name": "Account_227",
    "description": "Description for Account_227",
    "amount": 16
  },
  {
    "id": 228,
    "date": "2024-11-28",
    "account_name": "Account_228",
    "description": "Description for Account_228",
    "amount": -735
  },
  {
    "id": 229,
    "date": "2024-11-29",
    "account_name": "Account_229",
    "description": "Description for Account_229",
    "amount": -361
  },
  {
    "id": 230,
    "date": "2024-11-30",
    "account_name": "Account_230",
    "description": "Description for Account_230",
    "amount": 713
  },
  {
    "id": 231,
    "date": "2024-12-01",
    "account_name": "Account_231",
    "description": "Description for Account_231",
    "amount": 791
  },
  {
    "id": 232,
    "date": "2024-12-02",
    "account_name": "Account_232",
    "description": "Description for Account_232",
    "amount": 11
  },
  {
    "id": 233,
    "date": "2024-12-03",
    "account_name": "Account_233",
    "description": "Description for Account_233",
    "amount": -95
  },
  {
    "id": 234,
    "date": "2024-12-04",
    "account_name": "Account_234",
    "description": "Description for Account_234",
    "amount": -680
  },
  {
    "id": 235,
    "date": "2024-12-05",
    "account_name": "Account_235",
    "description": "Description for Account_235",
    "amount": -221
  },
  {
    "id": 236,
    "date": "2024-12-06",
    "account_name": "Account_236",
    "description": "Description for Account_236",
    "amount": -379
  },
  {
    "id": 237,
    "date": "2024-12-07",
    "account_name": "Account_237",
    "description": "Description for Account_237",
    "amount": 448
  },
  {
    "id": 238,
    "date": "2024-12-08",
    "account_name": "Account_238",
    "description": "Description for Account_238",
    "amount": 957
  },
  {
    "id": 239,
    "date": "2024-12-09",
    "account_name": "Account_239",
    "description": "Description for Account_239",
    "amount": -462
  },
  {
    "id": 240,
    "date": "2024-12-10",
    "account_name": "Account_240",
    "description": "Description for Account_240",
    "amount": 318
  },
  {
    "id": 241,
    "date": "2024-12-11",
    "account_name": "Account_241",
    "description": "Description for Account_241",
    "amount": -490
  },
  {
    "id": 242,
    "date": "2024-12-12",
    "account_name": "Account_242",
    "description": "Description for Account_242",
    "amount": -522
  },
  {
    "id": 243,
    "date": "2024-12-13",
    "account_name": "Account_243",
    "description": "Description for Account_243",
    "amount": 800
  },
  {
    "id": 244,
    "date": "2024-12-14",
    "account_name": "Account_244",
    "description": "Description for Account_244",
    "amount": -213
  },
  {
    "id": 245,
    "date": "2024-12-15",
    "account_name": "Account_245",
    "description": "Description for Account_245",
    "amount": -112
  },
  {
    "id": 246,
    "date": "2024-12-16",
    "account_name": "Account_246",
    "description": "Description for Account_246",
    "amount": 314
  },
  {
    "id": 247,
    "date": "2024-12-17",
    "account_name": "Account_247",
    "description": "Description for Account_247",
    "amount": -486
  },
  {
    "id": 248,
    "date": "2024-12-18",
    "account_name": "Account_248",
    "description": "Description for Account_248",
    "amount": -585
  },
  {
    "id": 249,
    "date": "2024-12-19",
    "account_name": "Account_249",
    "description": "Description for Account_249",
    "amount": -84
  },
  {
    "id": 250,
    "date": "2024-12-20",
    "account_name": "Account_250",
    "description": "Description for Account_250",
    "amount": 215
  },
  {
    "id": 251,
    "date": "2024-12-21",
    "account_name": "Account_251",
    "description": "Description for Account_251",
    "amount": 594
  },
  {
    "id": 252,
    "date": "2024-12-22",
    "account_name": "Account_252",
    "description": "Description for Account_252",
    "amount": 374
  },
  {
    "id": 253,
    "date": "2024-12-23",
    "account_name": "Account_253",
    "description": "Description for Account_253",
    "amount": -841
  },
  {
    "id": 254,
    "date": "2024-12-24",
    "account_name": "Account_254",
    "description": "Description for Account_254",
    "amount": 988
  },
  {
    "id": 255,
    "date": "2024-12-25",
    "account_name": "Account_255",
    "description": "Description for Account_255",
    "amount": 878
  },
  {
    "id": 256,
    "date": "2024-12-26",
    "account_name": "Account_256",
    "description": "Description for Account_256",
    "amount": 147
  },
  {
    "id": 257,
    "date": "2024-12-27",
    "account_name": "Account_257",
    "description": "Description for Account_257",
    "amount": 406
  },
  {
    "id": 258,
    "date": "2024-12-28",
    "account_name": "Account_258",
    "description": "Description for Account_258",
    "amount": -183
  },
  {
    "id": 259,
    "date": "2024-12-29",
    "account_name": "Account_259",
    "description": "Description for Account_259",
    "amount": 666
  },
  {
    "id": 260,
    "date": "2024-12-30",
    "account_name": "Account_260",
    "description": "Description for Account_260",
    "amount": 275
  },
  {
    "id": 261,
    "date": "2024-12-31",
    "account_name": "Account_261",
    "description": "Description for Account_261",
    "amount": 500
  },
  {
    "id": 262,
    "date": "2025-01-01",
    "account_name": "Account_262",
    "description": "Description for Account_262",
    "amount": -196
  },
  {
    "id": 263,
    "date": "2025-01-02",
    "account_name": "Account_263",
    "description": "Description for Account_263",
    "amount": -369
  },
  {
    "id": 264,
    "date": "2025-01-03",
    "account_name": "Account_264",
    "description": "Description for Account_264",
    "amount": 472
  },
  {
    "id": 265,
    "date": "2025-01-04",
    "account_name": "Account_265",
    "description": "Description for Account_265",
    "amount": 148
  },
  {
    "id": 266,
    "date": "2025-01-05",
    "account_name": "Account_266",
    "description": "Description for Account_266",
    "amount": 192
  },
  {
    "id": 267,
    "date": "2025-01-06",
    "account_name": "Account_267",
    "description": "Description for Account_267",
    "amount": -163
  },
  {
    "id": 268,
    "date": "2025-01-07",
    "account_name": "Account_268",
    "description": "Description for Account_268",
    "amount": -937
  },
  {
    "id": 269,
    "date": "2025-01-08",
    "account_name": "Account_269",
    "description": "Description for Account_269",
    "amount": -896
  },
  {
    "id": 270,
    "date": "2025-01-09",
    "account_name": "Account_270",
    "description": "Description for Account_270",
    "amount": 328
  },
  {
    "id": 271,
    "date": "2025-01-10",
    "account_name": "Account_271",
    "description": "Description for Account_271",
    "amount": -456
  },
  {
    "id": 272,
    "date": "2025-01-11",
    "account_name": "Account_272",
    "description": "Description for Account_272",
    "amount": -628
  },
  {
    "id": 273,
    "date": "2025-01-12",
    "account_name": "Account_273",
    "description": "Description for Account_273",
    "amount": -626
  },
  {
    "id": 274,
    "date": "2025-01-13",
    "account_name": "Account_274",
    "description": "Description for Account_274",
    "amount": -50
  },
  {
    "id": 275,
    "date": "2025-01-14",
    "account_name": "Account_275",
    "description": "Description for Account_275",
    "amount": -898
  },
  {
    "id": 276,
    "date": "2025-01-15",
    "account_name": "Account_276",
    "description": "Description for Account_276",
    "amount": -828
  },
  {
    "id": 277,
    "date": "2025-01-16",
    "account_name": "Account_277",
    "description": "Description for Account_277",
    "amount": 592
  },
  {
    "id": 278,
    "date": "2025-01-17",
    "account_name": "Account_278",
    "description": "Description for Account_278",
    "amount": -153
  },
  {
    "id": 279,
    "date": "2025-01-18",
    "account_name": "Account_279",
    "description": "Description for Account_279",
    "amount": 605
  },
  {
    "id": 280,
    "date": "2025-01-19",
    "account_name": "Account_280",
    "description": "Description for Account_280",
    "amount": -684
  },
  {
    "id": 281,
    "date": "2025-01-20",
    "account_name": "Account_281",
    "description": "Description for Account_281",
    "amount": -743
  },
  {
    "id": 282,
    "date": "2025-01-21",
    "account_name": "Account_282",
    "description": "Description for Account_282",
    "amount": 652
  },
  {
    "id": 283,
    "date": "2025-01-22",
    "account_name": "Account_283",
    "description": "Description for Account_283",
    "amount": -425
  },
  {
    "id": 284,
    "date": "2025-01-23",
    "account_name": "Account_284",
    "description": "Description for Account_284",
    "amount": 670
  },
  {
    "id": 285,
    "date": "2025-01-24",
    "account_name": "Account_285",
    "description": "Description for Account_285",
    "amount": -313
  },
  {
    "id": 286,
    "date": "2025-01-25",
    "account_name": "Account_286",
    "description": "Description for Account_286",
    "amount": -825
  },
  {
    "id": 287,
    "date": "2025-01-26",
    "account_name": "Account_287",
    "description": "Description for Account_287",
    "amount": -962
  },
  {
    "id": 288,
    "date": "2025-01-27",
    "account_name": "Account_288",
    "description": "Description for Account_288",
    "amount": -344
  },
  {
    "id": 289,
    "date": "2025-01-28",
    "account_name": "Account_289",
    "description": "Description for Account_289",
    "amount": -866
  },
  {
    "id": 290,
    "date": "2025-01-29",
    "account_name": "Account_290",
    "description": "Description for Account_290",
    "amount": -462
  },
  {
    "id": 291,
    "date": "2025-01-30",
    "account_name": "Account_291",
    "description": "Description for Account_291",
    "amount": -20
  },
  {
    "id": 292,
    "date": "2025-01-31",
    "account_name": "Account_292",
    "description": "Description for Account_292",
    "amount": 582
  },
  {
    "id": 293,
    "date": "2025-02-01",
    "account_name": "Account_293",
    "description": "Description for Account_293",
    "amount": 293
  },
  {
    "id": 294,
    "date": "2025-02-02",
    "account_name": "Account_294",
    "description": "Description for Account_294",
    "amount": -875
  },
  {
    "id": 295,
    "date": "2025-02-03",
    "account_name": "Account_295",
    "description": "Description for Account_295",
    "amount": -952
  },
  {
    "id": 296,
    "date": "2025-02-04",
    "account_name": "Account_296",
    "description": "Description for Account_296",
    "amount": 455
  },
  {
    "id": 297,
    "date": "2025-02-05",
    "account_name": "Account_297",
    "description": "Description for Account_297",
    "amount": 746
  },
  {
    "id": 298,
    "date": "2025-02-06",
    "account_name": "Account_298",
    "description": "Description for Account_298",
    "amount": 26
  },
  {
    "id": 299,
    "date": "2025-02-07",
    "account_name": "Account_299",
    "description": "Description for Account_299",
    "amount": 265
  },
  {
    "id": 300,
    "date": "2025-02-08",
    "account_name": "Account_300",
    "description": "Description for Account_300",
    "amount": -554
  },
  {
    "id": 301,
    "date": "2025-02-09",
    "account_name": "Account_301",
    "description": "Description for Account_301",
    "amount": -83
  },
  {
    "id": 302,
    "date": "2025-02-10",
    "account_name": "Account_302",
    "description": "Description for Account_302",
    "amount": -17
  },
  {
    "id": 303,
    "date": "2025-02-11",
    "account_name": "Account_303",
    "description": "Description for Account_303",
    "amount": -788
  },
  {
    "id": 304,
    "date": "2025-02-12",
    "account_name": "Account_304",
    "description": "Description for Account_304",
    "amount": 712
  },
  {
    "id": 305,
    "date": "2025-02-13",
    "account_name": "Account_305",
    "description": "Description for Account_305",
    "amount": 827
  },
  {
    "id": 306,
    "date": "2025-02-14",
    "account_name": "Account_306",
    "description": "Description for Account_306",
    "amount": -566
  },
  {
    "id": 307,
    "date": "2025-02-15",
    "account_name": "Account_307",
    "description": "Description for Account_307",
    "amount": 70
  },
  {
    "id": 308,
    "date": "2025-02-16",
    "account_name": "Account_308",
    "description": "Description for Account_308",
    "amount": -425
  },
  {
    "id": 309,
    "date": "2025-02-17",
    "account_name": "Account_309",
    "description": "Description for Account_309",
    "amount": 936
  },
  {
    "id": 310,
    "date": "2025-02-18",
    "account_name": "Account_310",
    "description": "Description for Account_310",
    "amount": -34
  },
  {
    "id": 311,
    "date": "2025-02-19",
    "account_name": "Account_311",
    "description": "Description for Account_311",
    "amount": -606
  },
  {
    "id": 312,
    "date": "2025-02-20",
    "account_name": "Account_312",
    "description": "Description for Account_312",
    "amount": -731
  },
  {
    "id": 313,
    "date": "2025-02-21",
    "account_name": "Account_313",
    "description": "Description for Account_313",
    "amount": -206
  },
  {
    "id": 314,
    "date": "2025-02-22",
    "account_name": "Account_314",
    "description": "Description for Account_314",
    "amount": -5
  },
  {
    "id": 315,
    "date": "2025-02-23",
    "account_name": "Account_315",
    "description": "Description for Account_315",
    "amount": 376
  },
  {
    "id": 316,
    "date": "2025-02-24",
    "account_name": "Account_316",
    "description": "Description for Account_316",
    "amount": -172
  },
  {
    "id": 317,
    "date": "2025-02-25",
    "account_name": "Account_317",
    "description": "Description for Account_317",
    "amount": 999
  },
  {
    "id": 318,
    "date": "2025-02-26",
    "account_name": "Account_318",
    "description": "Description for Account_318",
    "amount": 450
  },
  {
    "id": 319,
    "date": "2025-02-27",
    "account_name": "Account_319",
    "description": "Description for Account_319",
    "amount": 697
  },
  {
    "id": 320,
    "date": "2025-02-28",
    "account_name": "Account_320",
    "description": "Description for Account_320",
    "amount": -781
  },
  {
    "id": 321,
    "date": "2025-03-01",
    "account_name": "Account_321",
    "description": "Description for Account_321",
    "amount": 862
  },
  {
    "id": 322,
    "date": "2025-03-02",
    "account_name": "Account_322",
    "description": "Description for Account_322",
    "amount": -883
  },
  {
    "id": 323,
    "date": "2025-03-03",
    "account_name": "Account_323",
    "description": "Description for Account_323",
    "amount": -317
  },
  {
    "id": 324,
    "date": "2025-03-04",
    "account_name": "Account_324",
    "description": "Description for Account_324",
    "amount": 612
  },
  {
    "id": 325,
    "date": "2025-03-05",
    "account_name": "Account_325",
    "description": "Description for Account_325",
    "amount": -765
  },
  {
    "id": 326,
    "date": "2025-03-06",
    "account_name": "Account_326",
    "description": "Description for Account_326",
    "amount": -279
  },
  {
    "id": 327,
    "date": "2025-03-07",
    "account_name": "Account_327",
    "description": "Description for Account_327",
    "amount": -487
  },
  {
    "id": 328,
    "date": "2025-03-08",
    "account_name": "Account_328",
    "description": "Description for Account_328",
    "amount": -237
  },
  {
    "id": 329,
    "date": "2025-03-09",
    "account_name": "Account_329",
    "description": "Description for Account_329",
    "amount": -831
  },
  {
    "id": 330,
    "date": "2025-03-10",
    "account_name": "Account_330",
    "description": "Description for Account_330",
    "amount": 940
  },
  {
    "id": 331,
    "date": "2025-03-11",
    "account_name": "Account_331",
    "description": "Description for Account_331",
    "amount": 660
  },
  {
    "id": 332,
    "date": "2025-03-12",
    "account_name": "Account_332",
    "description": "Description for Account_332",
    "amount": 818
  },
  {
    "id": 333,
    "date": "2025-03-13",
    "account_name": "Account_333",
    "description": "Description for Account_333",
    "amount": -113
  },
  {
    "id": 334,
    "date": "2025-03-14",
    "account_name": "Account_334",
    "description": "Description for Account_334",
    "amount": -444
  },
  {
    "id": 335,
    "date": "2025-03-15",
    "account_name": "Account_335",
    "description": "Description for Account_335",
    "amount": 518
  },
  {
    "id": 336,
    "date": "2025-03-16",
    "account_name": "Account_336",
    "description": "Description for Account_336",
    "amount": 958
  },
  {
    "id": 337,
    "date": "2025-03-17",
    "account_name": "Account_337",
    "description": "Description for Account_337",
    "amount": -478
  },
  {
    "id": 338,
    "date": "2025-03-18",
    "account_name": "Account_338",
    "description": "Description for Account_338",
    "amount": 722
  },
  {
    "id": 339,
    "date": "2025-03-19",
    "account_name": "Account_339",
    "description": "Description for Account_339",
    "amount": 442
  },
  {
    "id": 340,
    "date": "2025-03-20",
    "account_name": "Account_340",
    "description": "Description for Account_340",
    "amount": -979
  },
  {
    "id": 341,
    "date": "2025-03-21",
    "account_name": "Account_341",
    "description": "Description for Account_341",
    "amount": 790
  },
  {
    "id": 342,
    "date": "2025-03-22",
    "account_name": "Account_342",
    "description": "Description for Account_342",
    "amount": -616
  },
  {
    "id": 343,
    "date": "2025-03-23",
    "account_name": "Account_343",
    "description": "Description for Account_343",
    "amount": -485
  },
  {
    "id": 344,
    "date": "2025-03-24",
    "account_name": "Account_344",
    "description": "Description for Account_344",
    "amount": -647
  },
  {
    "id": 345,
    "date": "2025-03-25",
    "account_name": "Account_345",
    "description": "Description for Account_345",
    "amount": -619
  },
  {
    "id": 346,
    "date": "2025-03-26",
    "account_name": "Account_346",
    "description": "Description for Account_346",
    "amount": 251
  },
  {
    "id": 347,
    "date": "2025-03-27",
    "account_name": "Account_347",
    "description": "Description for Account_347",
    "amount": -274
  },
  {
    "id": 348,
    "date": "2025-03-28",
    "account_name": "Account_348",
    "description": "Description for Account_348",
    "amount": -258
  },
  {
    "id": 349,
    "date": "2025-03-29",
    "account_name": "Account_349",
    "description": "Description for Account_349",
    "amount": -873
  },
  {
    "id": 350,
    "date": "2025-03-30",
    "account_name": "Account_350",
    "description": "Description for Account_350",
    "amount": -52
  },
  {
    "id": 351,
    "date": "2025-03-31",
    "account_name": "Account_351",
    "description": "Description for Account_351",
    "amount": -148
  },
  {
    "id": 352,
    "date": "2025-04-01",
    "account_name": "Account_352",
    "description": "Description for Account_352",
    "amount": -86
  },
  {
    "id": 353,
    "date": "2025-04-02",
    "account_name": "Account_353",
    "description": "Description for Account_353",
    "amount": 271
  },
  {
    "id": 354,
    "date": "2025-04-03",
    "account_name": "Account_354",
    "description": "Description for Account_354",
    "amount": 87
  },
  {
    "id": 355,
    "date": "2025-04-04",
    "account_name": "Account_355",
    "description": "Description for Account_355",
    "amount": -389
  },
  {
    "id": 356,
    "date": "2025-04-05",
    "account_name": "Account_356",
    "description": "Description for Account_356",
    "amount": 104
  },
  {
    "id": 357,
    "date": "2025-04-06",
    "account_name": "Account_357",
    "description": "Description for Account_357",
    "amount": -772
  },
  {
    "id": 358,
    "date": "2025-04-07",
    "account_name": "Account_358",
    "description": "Description for Account_358",
    "amount": 858
  },
  {
    "id": 359,
    "date": "2025-04-08",
    "account_name": "Account_359",
    "description": "Description for Account_359",
    "amount": 40
  },
  {
    "id": 360,
    "date": "2025-04-09",
    "account_name": "Account_360",
    "description": "Description for Account_360",
    "amount": 208
  },
  {
    "id": 361,
    "date": "2025-04-10",
    "account_name": "Account_361",
    "description": "Description for Account_361",
    "amount": -159
  },
  {
    "id": 362,
    "date": "2025-04-11",
    "account_name": "Account_362",
    "description": "Description for Account_362",
    "amount": 793
  },
  {
    "id": 363,
    "date": "2025-04-12",
    "account_name": "Account_363",
    "description": "Description for Account_363",
    "amount": -532
  },
  {
    "id": 364,
    "date": "2025-04-13",
    "account_name": "Account_364",
    "description": "Description for Account_364",
    "amount": -472
  },
  {
    "id": 365,
    "date": "2025-04-14",
    "account_name": "Account_365",
    "description": "Description for Account_365",
    "amount": -72
  }
]
